kisters/water/hydraulic_network/models/__init__.py
kisters/water/hydraulic_network/models/_version.py
kisters/water/hydraulic_network/models/element.py
kisters/water/hydraulic_network/models/link.py
kisters/water/hydraulic_network/models/metadata.py
kisters/water/hydraulic_network/models/node.py
kisters.water.hydraulic_network.models-0.0.4.dist-info/LICENSE
kisters.water.hydraulic_network.models-0.0.4.dist-info/METADATA
kisters.water.hydraulic_network.models-0.0.4.dist-info/WHEEL
kisters.water.hydraulic_network.models-0.0.4.dist-info/top_level.txt
kisters.water.hydraulic_network.models-0.0.4.dist-info/RECORD
